tests/__init__.py
tests/func_examples.py
tests/test_pool.py
tests/test_process.py
tests/live/__init__.py
tests/live/test_live_discomp.py
tests/live/test_files/__init__.py
tests/live/test_files/pool_helper.py
tests/live/test_files/process_helper.py
discomp-1.25.0.dist-info/METADATA
discomp-1.25.0.dist-info/WHEEL
discomp-1.25.0.dist-info/top_level.txt
discomp-1.25.0.dist-info/RECORD
