Metadata-Version: 2.1
Name: discomp
Version: 1.25.0
Summary: Run Python jobs in parallel on the cloud using DISCO
Home-page: https://github.com/Iqoqo/python-sdk
Author: Disco
Author-email: contact@dis.co
License: UNKNOWN
Platform: UNKNOWN
Classifier: Programming Language :: Python :: 3.6
Classifier: Programming Language :: Python :: 3.7
Classifier: Programming Language :: Python :: 3.8
Classifier: Operating System :: OS Independent
Requires-Python: >=3.6
Requires-Dist: dill (==0.3.1.1)
Requires-Dist: disco
